glaze/__init__.py
glaze/__main__.py
glaze/render.py
glaze/utils.py
glaze-0.3.0.dist-info/LICENSE
glaze-0.3.0.dist-info/METADATA
glaze-0.3.0.dist-info/WHEEL
glaze-0.3.0.dist-info/entry_points.txt
glaze-0.3.0.dist-info/top_level.txt
glaze-0.3.0.dist-info/RECORD
