Metadata-Version: 2.1
Name: glaze
Version: 0.3.0
Summary: A Python library and command line tool for rendering algorithmically-generated fonts and typefaces.
Home-page: https://github.com/font-bakers/glaze
Maintainer: The Font Bakers
License: MIT
Project-URL: Documentation, https://font-bakers.github.io/glaze/
Project-URL: Issue Tracker, https://github.com/font-bakers/glaze/issues
Platform: UNKNOWN
Classifier: Development Status :: 3 - Alpha
Classifier: Environment :: Console
Classifier: License :: OSI Approved :: MIT License
Classifier: Natural Language :: English
Classifier: Operating System :: OS Independent
Classifier: Programming Language :: Python
Classifier: Programming Language :: Python :: 3
Classifier: Programming Language :: Python :: 3.5
Classifier: Topic :: Scientific/Engineering
Classifier: Topic :: Text Processing :: Fonts
Requires-Python: >=3.5.2
Requires-Dist: absl-py
Requires-Dist: bezier
Requires-Dist: matplotlib
Requires-Dist: numpy
Requires-Dist: tqdm
